{
  "cards": [
    {
      "status": "OFFLINE ",
      "title": "fdfdhdfh",
      "description": "OFFLINE ",
      "boardId": 1,
      "columnId": 0,
      "id": 32
    }
  ],
  "boards": [
    {
      "boardTitle": "fghfgh",
      "boardDescription": "",
      "id": 1
    },
    {
      "boardTitle": "xcv",
      "boardDescription": "",
      "id": 2
    }
  ],
  "columns": [
    {
      "id": 0,
      "title": "qweqwe",
      "boardId": 1
    }
  ],
  "login": [
    {}
  ],
  "labels": [
    {
      "id": 0,
      "title": "testowy",
      "color": "#ff0123"
    }
  ]
}